fairly/__init__.py
fairly/diff.py
fairly/metadata.py
fairly/person.py
fairly/cli/__init__.py
fairly/cli/config.py
fairly/cli/dataset.py
fairly/client/__init__.py
fairly/client/dataverse.py
fairly/client/djehuty.py
fairly/client/figshare.py
fairly/client/invenio.py
fairly/client/zenodo.py
fairly/data/config.json
fairly/data/languages/ISO-639-2_8859-1.tab
fairly/data/languages/ISO-639-2_UTF-8.tab
fairly/data/languages/ISO-639-3_8859-1.tab
fairly/data/languages/ISO-639-3_UTF-8.tab
fairly/data/templates/default.yaml
fairly/data/templates/figshare.yaml
fairly/data/templates/zenodo.yaml
fairly/dataset/__init__.py
fairly/dataset/local.py
fairly/dataset/remote.py
fairly/file/__init__.py
fairly/file/local.py
fairly/file/remote.py
fairly-1.0.1.dist-info/METADATA
fairly-1.0.1.dist-info/WHEEL
fairly-1.0.1.dist-info/entry_points.txt
fairly-1.0.1.dist-info/licenses/LICENSE
fairly-1.0.1.dist-info/RECORD
