Metadata-Version: 2.3
Name: fairly
Version: 1.0.1
Summary: A package to create, publish, and download research datasets
Project-URL: Homepage, https://github.com/ITC-CRIB/fairly
Project-URL: Bug Tracker, https://github.com/ITC-CRIB/fairly/issues
Project-URL: Documentation, https://fairly.readthedocs.io
Project-URL: Funding, https://nwo.nl/en/researchprogrammes/open-science/open-science-fund
Author-email: Serkan Girgin <s.girgin@utwente.nl>, Manuel Garcia Alvarez <m.g.garciaalvarez@tudelft.nl>, Jose Urra Llanusa <j.c.urrallanusa@tudelft.nl>
License: MIT License
License-File: LICENSE
Keywords: data management,fairly,open science,research data
Classifier: License :: OSI Approved :: MIT License
Classifier: Operating System :: OS Independent
Classifier: Programming Language :: Python :: 3
Requires-Python: >=3.8
Requires-Dist: python-dateutil
Requires-Dist: requests
Requires-Dist: requests-toolbelt>=1.0.0
Requires-Dist: rich
Requires-Dist: ruamel-yaml>=0.17.26
Requires-Dist: typer>=0.9.0
Provides-Extra: dev
Requires-Dist: build; extra == 'dev'
Requires-Dist: hatch; extra == 'dev'
Requires-Dist: pytest; extra == 'dev'
Requires-Dist: pytest-cov; extra == 'dev'
Requires-Dist: python-dotenv; extra == 'dev'
